{
	"name": "AzureSqlDatabaseSinkDataset1",
	"properties": {
		"description": "Connection to your destination data store.",
		"linkedServiceName": {
			"referenceName": "linkedService5",
			"type": "LinkedServiceReference"
		},
		"parameters": {
			"sinkTableName": {
				"type": "string",
				"defaultValue": "Emp"
			}
		},
		"annotations": [],
		"type": "AzureSqlTable",
		"schema": [
			{
				"name": "_c0",
				"type": "nvarchar"
			},
			{
				"name": "_c1",
				"type": "nvarchar"
			}
		],
		"typeProperties": {
			"schema": "dbo",
			"table": "Emp"
		}
	}
}